eloh/client.py
eloh/common.py
eloh/server.py
eloh-0.0.1.dist-info/METADATA
eloh-0.0.1.dist-info/RECORD
eloh-0.0.1.dist-info/WHEEL
eloh-0.0.1.dist-info/entry_points.txt
eloh-0.0.1.dist-info/top_level.txt
