Metadata-Version: 2.1
Name: eloh
Version: 0.0.1
Summary: Send files via hole-punching
Home-page: UNKNOWN
Author: Louis Abraham
Author-email: louis.abraham@yahoo.fr
License: MIT
Platform: UNKNOWN
Requires-Python: >=3.6
